boring_math/homepage/__init__.py
boring_math/homepage/compatible_versions.py
boring_math/homepage/development.py
boring_math/homepage/docs.py
boring_math/homepage/intro.py
boring_math/homepage/overview.py
boring_math/homepage/py.typed
boring_math/homepage/top_level_releases.py
boring_math-2.0.1.dist-info/licenses/LICENSE
boring_math-2.0.1.dist-info/WHEEL
boring_math-2.0.1.dist-info/METADATA
boring_math-2.0.1.dist-info/RECORD
