Metadata-Version: 2.4
Name: boring-math
Version: 2.0.1
Summary: Purpose boring-math PyPI Project
Keywords: mathematics,special functions
Author-email: "Geoffrey R. Scheller" <geoffrey@scheller.com>
Requires-Python: >=3.13
Classifier: Development Status :: 3 - Alpha
Classifier: Intended Audience :: Education
Classifier: License :: OSI Approved :: Apache Software License
Classifier: Operating System :: OS Independent
Classifier: Programming Language :: Python :: 3.13
Classifier: Typing :: Typed
License-File: LICENSE
Project-URL: Changelog, https://github.com/grscheller/boring-math/blob/main/CHANGELOG.rst
Project-URL: Homepage, https://grscheller.github.io/boring-math/homepage/build/html/
Project-URL: Source, https://github.com/grscheller/boring-math
